{
    "files.exclude": {
        "**/.git": true,
        "**/.svn": true,
        "**/.hg": true,
        "**/CVS": true,
        "**/.DS_Store": true,
        "**/node_modules/**": true
    },
    "editor.glyphMargin": false,
    "editor.wordWrap": "on",
    "window.titleBarStyle": "native",
    "workbench.editor.enablePreview": false,
    "workbench.editor.enablePreviewFromQuickOpen": false,
    "vim.insertModeKeyBindings": [
        {
            "before": [
                "j",
                "k"
            ],
            "after": [
                "<Esc>"
            ]
        }
    ],
    "vim.normalModeKeyBindings": [
        {
            "before": [
                "J"
            ],
            "after": [
                "<C-d>"
            ]
        },
        {
            "before": [
                "K"
            ],
            "after": [
                "<C-u>"
            ]
        },
        {
            "before": [
                "H"
            ],
            "after": [
                "g",
                "T"
            ]
        },
        {
            "before": [
                "L"
            ],
            "after": [
                "g",
                "t"
            ]
        }
    ],
    "vim.useCtrlKeys": true,
    "emmet.triggerExpansionOnTab": true,
    "emmet.includeLanguages": {
        "javascript": "javascriptreact"
    },
    "window.zoomLevel": -1,
    "vim.useSystemClipboard": true,
    "editor.minimap.enabled": false,
    "editor.fontSize": 18,
    "editor.letterSpacing": -0.2,
    "editor.formatOnPaste": true,
    "editor.formatOnSave": true,
    "files.autoSave": "onFocusChange",
    "files.trimFinalNewlines": true,
    "window.menuBarVisibility": "toggle",
    "workbench.sideBar.location": "right",
    "workbench.iconTheme": "material-icon-theme",
    "python.jediEnabled": false,
    "python.linting.enabled": false,
    "python.pythonPath": "/usr/bin/python3.7",
    "editor.lineNumbers": "relative",
    "workbench.colorTheme": "Gruvbox Dark Medium",
    "[python]": {},
    "explorer.confirmDelete": false,
    "workbench.statusBar.feedback.visible": false,
    "workbench.editor.labelFormat": "short",
    "explorer.confirmDragAndDrop": false,
    "breadcrumbs.enabled": true,
    "javascript.updateImportsOnFileMove.enabled": "always"
}
